mppf-1.7.dist-info/METADATA
mppf-1.7.dist-info/RECORD
mppf-1.7.dist-info/WHEEL
mppf-1.7.dist-info/entry_points.txt
mppf-1.7.dist-info/top_level.txt
source/__init__.py
source/main.py
