Metadata-Version: 2.1
Name: mppf
Version: 1.7
Summary: A simple command line tool for managing provisioning profiles.
Home-page: https://github.com/cjsliuj/mppf
Author: nsrx
Author-email: cjsliuj@163.com
License: UNKNOWN
Platform: any
Requires-Python: >=3.5
Requires-Dist: pyopenssl
